pdfuncdemo/__init__.py
pdfuncdemo-0.0.3.dist-info/METADATA
pdfuncdemo-0.0.3.dist-info/WHEEL
pdfuncdemo-0.0.3.dist-info/RECORD
